LICENSE
MANIFEST.in
setup.py
Flask_Maple.egg-info/PKG-INFO
Flask_Maple.egg-info/SOURCES.txt
Flask_Maple.egg-info/dependency_links.txt
Flask_Maple.egg-info/not-zip-safe
Flask_Maple.egg-info/requires.txt
Flask_Maple.egg-info/top_level.txt
flask_maple/__init__.py
flask_maple/app.py
flask_maple/babel.py
flask_maple/bootstrap.py
flask_maple/captcha.py
flask_maple/error.py
flask_maple/form.py
flask_maple/json.py
flask_maple/lazy.py
flask_maple/log.py
flask_maple/mail.py
flask_maple/middleware.py
flask_maple/redis.py
flask_maple/response.py
flask_maple/serializer.py
flask_maple/utils.py
flask_maple/views.py
flask_maple/auth/__init__.py
flask_maple/auth/models.py
flask_maple/auth/views.py
flask_maple/models/__init__.py
flask_maple/models/permission.py
flask_maple/static/css/honmaple.css
flask_maple/static/images/ship.png
flask_maple/static/js/login.js
flask_maple/templates/auth/forget.html
flask_maple/templates/auth/login.html
flask_maple/templates/auth/register.html
flask_maple/templates/maple/auth.html
flask_maple/templates/maple/base.html
flask_maple/templates/maple/captcha.html
flask_maple/templates/maple/footer.html
flask_maple/templates/maple/install.html
flask_maple/templates/maple/paginate.html
flask_maple/templates/templet/email.html
flask_maple/templates/templet/error_403.html
flask_maple/templates/templet/error_404.html
flask_maple/templates/templet/error_500.html
flask_maple/templates/templet/forget.html
flask_maple/translations/__init__.py
flask_maple/translations/zh/LC_MESSAGES/messages.mo
flask_maple/translations/zh/LC_MESSAGES/messages.po