Metadata-Version: 1.1
Name: Flask-Maple
Version: 0.5.6
Summary: captcha ,bootstrap,easy login and more flask tips.
Home-page: https://github.com/honmaple/flask-maple
Author: honmaple
Author-email: mail@honmaple.com
License: BSD
Platform: any
Classifier: Environment :: Web Environment
Classifier: Intended Audience :: Developers
Classifier: License :: OSI Approved :: BSD License
Classifier: Operating System :: OS Independent
Classifier: Programming Language :: Python
Classifier: Topic :: Internet :: WWW/HTTP :: Dynamic Content
Classifier: Topic :: Software Development :: Libraries :: Python Modules
